newton_polygon/__init__.py
newton_polygon/polygon.py
Newton_Polygon-0.0.7.dist-info/LICENSE
Newton_Polygon-0.0.7.dist-info/METADATA
Newton_Polygon-0.0.7.dist-info/WHEEL
Newton_Polygon-0.0.7.dist-info/top_level.txt
Newton_Polygon-0.0.7.dist-info/RECORD
