Metadata-Version: 2.1
Name: Newton-Polygon
Version: 0.0.7
Summary: Python power geometry package.
Home-page: https://github.com/Garrisonmond/Newton-Polygon/tree/main
Author: Ivan Kuznetsov
Author-email: maxbeyn@icloud.com
Classifier: Programming Language :: Python :: 3.7
Classifier: License :: OSI Approved :: GNU General Public License v3 (GPLv3)
License-File: LICENSE
Requires-Dist: matplotlib
Requires-Dist: seaborn
Requires-Dist: wolframclient
